[1,["fbLE78G/xPwIczoudswIov@6c48a"],["_textureSource"],["cc.SpriteFrame"],0,[{"name":"ESR_CONTAINER_OBJECTIVE","rect":{"x":0,"y":0,"width":1035,"height":1628},"offset":{"x":0,"y":0},"originalSize":{"width":1035,"height":1628},"rotated":false,"capInsets":[0,0,0,0],"vertices":{"rawPosition":[-517.5,-814,0,517.5,-814,0,-517.5,814,0,517.5,814,0],"indexes":[0,1,2,2,1,3],"uv":[0,1628,1035,1628,0,0,1035,0],"nuv":[0,0,1,0,0,1,1,1],"minPos":{"x":-517.5,"y":-814,"z":0},"maxPos":{"x":517.5,"y":814,"z":0}},"packable":true,"pixelsToUnit":100,"pivot":{"x":0.5,"y":0.5},"meshType":0}],[0],0,[0],[0],[0]]
